{"keys":[{"keyName":"Precourse","URL":"http://res.cloudinary.com/dn4vqx2gu/image/upload/v1488672122/rzcckliek05taq6a2pul.jpg","answers":"{\"1\":[\"a\"],\"2\":[\"c\"],\"3\":[\"b\"],\"4\":[\"d\"],\"5\":[\"d\"],\"6\":[\"c\"],\"7\":[\"d\"],\"8\":[\"b\"],\"9\":[\"c\"],\"10\":[\"c\"],\"11\":[\"a\"],\"12\":[\"d\"],\"13\":[\"d\"],\"14\":[\"c\",\"e\"],\"15\":[\"a\"],\"16\":[\"a\"],\"17\":[\"d\"],\"18\":[\"d\"],\"19\":[\"e\"],\"20\":[\"c\"],\"21\":[\"a\"],\"22\":[\"c\"],\"23\":[\"c\"],\"24\":[\"b\"],\"25\":[\"d\"],\"26\":[\"c\"],\"27\":[\"d\"],\"28\":[\"e\"]}","ClassId":1,"TeacherId":1},{"keyName":"Midterm 1","URL":"http://res.cloudinary.com/dn4vqx2gu/image/upload/v1488672122/rzcckliek05taq6a2pul.jpg","answers":"{\"1\":[\"b\"],\"2\":[\"e\"],\"3\":[\"a\"],\"4\":[\"c\"],\"5\":[\"c\"],\"6\":[\"a\"],\"7\":[\"e\"],\"8\":[\"a\"],\"9\":[\"a\"],\"10\":[\"d\"],\"11\":[\"e\"],\"12\":[\"b\"],\"13\":[\"e\"],\"14\":[\"a\",\"d\"],\"15\":[\"e\"],\"16\":[\"a\"],\"17\":[\"a\"],\"18\":[\"a\"],\"19\":[\"b\"],\"20\":[\"d\"],\"21\":[\"d\"],\"22\":[\"b\"],\"23\":[\"e\"],\"24\":[\"d\"],\"25\":[\"c\"],\"26\":[\"a\"],\"27\":[\"e\"],\"28\":[\"b\"]}","ClassId":1,"TeacherId":1},{"keyName":"Midterm 2","URL":"http://res.cloudinary.com/dn4vqx2gu/image/upload/v1488672122/rzcckliek05taq6a2pul.jpg","answers":"{\"1\":[\"b\"],\"2\":[\"c\"],\"3\":[\"c\"],\"4\":[\"e\"],\"5\":[\"e\"],\"6\":[\"d\"],\"7\":[\"c\"],\"8\":[\"c\"],\"9\":[\"e\"],\"10\":[\"b\"],\"11\":[\"a\"],\"12\":[\"d\"],\"13\":[\"a\"],\"14\":[\"c\",\"c\"],\"15\":[\"c\"],\"16\":[\"a\"],\"17\":[\"e\"],\"18\":[\"e\"],\"19\":[\"b\"],\"20\":[\"a\"],\"21\":[\"a\"],\"22\":[\"d\"],\"23\":[\"e\"],\"24\":[\"a\"],\"25\":[\"e\"],\"26\":[\"d\"],\"27\":[\"c\"],\"28\":[\"e\"]}","ClassId":1,"TeacherId":1},{"keyName":"Final","URL":"http://res.cloudinary.com/dn4vqx2gu/image/upload/v1488672122/rzcckliek05taq6a2pul.jpg","answers":"{\"1\":[\"a\"],\"2\":[\"d\"],\"3\":[\"b\"],\"4\":[\"a\"],\"5\":[\"a\"],\"6\":[\"a\"],\"7\":[\"d\"],\"8\":[\"c\"],\"9\":[\"c\"],\"10\":[\"c\"],\"11\":[\"b\"],\"12\":[\"e\"],\"13\":[\"e\"],\"14\":[\"c\",\"e\"],\"15\":[\"b\"],\"16\":[\"a\"],\"17\":[\"a\"],\"18\":[\"d\"],\"19\":[\"c\"],\"20\":[\"e\"],\"21\":[\"c\"],\"22\":[\"a\"],\"23\":[\"c\"],\"24\":[\"e\"],\"25\":[\"b\"],\"26\":[\"a\"],\"27\":[\"d\"],\"28\":[\"e\"]}","ClassId":1,"TeacherId":1}]}